solathon/__init__.py
solathon/async_client.py
solathon/client.py
solathon/core/__init__.py
solathon/core/http.py
solathon/core/instructions.py
solathon/core/layouts.py
solathon/core/message.py
solathon/core/types/__init__.py
solathon/core/types/account_info.py
solathon/core/types/block.py
solathon/core/types/cluster_node.py
solathon/core/types/epoch.py
solathon/core/types/inflation.py
solathon/keypair.py
solathon/publickey.py
solathon/solana_pay/__init__.py
solathon/solana_pay/create_qr.py
solathon/solana_pay/create_transfer.py
solathon/solana_pay/encode_url.py
solathon/solana_pay/fetch_transaction.py
solathon/solana_pay/find_reference.py
solathon/solana_pay/parse_url.py
solathon/solana_pay/qr-logo.png
solathon/solana_pay/types.py
solathon/solana_pay/validate_transfer.py
solathon/transaction.py
solathon/utils.py
solathon-1.0.6.dist-info/LICENSE
solathon-1.0.6.dist-info/METADATA
solathon-1.0.6.dist-info/WHEEL
solathon-1.0.6.dist-info/RECORD
