Metadata-Version: 2.1
Name: solathon
Version: 1.0.6
Summary: High performance, easy to use and feature-rich Solana SDK for Python.
Home-page: https://github.com/GitBolt/solathon
License: MIT
Keywords: solana,web3,sdk,blockchain,crypto
Author: GitBolt
Requires-Python: >=3.8,<4.0
Classifier: Intended Audience :: Developers
Classifier: License :: OSI Approved :: MIT License
Classifier: Operating System :: OS Independent
Classifier: Programming Language :: Python :: 3
Classifier: Programming Language :: Python :: 3.8
Classifier: Programming Language :: Python :: 3.9
Classifier: Programming Language :: Python :: 3.10
Classifier: Programming Language :: Python :: 3.11
Classifier: Programming Language :: Python :: 3.12
Classifier: Programming Language :: Python :: 3.13
Classifier: Topic :: Software Development
Classifier: Topic :: Software Development :: Libraries :: Python Modules
Requires-Dist: PyNaCl (>=1.5.0,<2.0.0)
Requires-Dist: base58 (>=2.1.1,<3.0.0)
Requires-Dist: construct (>=2.10.67,<3.0.0)
Requires-Dist: httpx (>=0.27.2,<0.28.0)
Requires-Dist: pillow (>=10.2.0,<11.0.0)
Requires-Dist: qrcode (>=7.4.2,<8.0.0)
Requires-Dist: typing-extensions (>=4.1.1,<5.0.0) ; python_version == "3.10"
Project-URL: Repository, https://github.com/GitBolt/solathon
